{
  "name": "profiles/perfil-lentes-DG.jpg",
  "bucket": "healhty-food-2023-2024.appspot.com",
  "metageneration": 1,
  "generation": 1690885056984,
  "contentType": "image/jpeg",
  "storageClass": "STANDARD",
  "contentDisposition": "inline",
  "downloadTokens": [
    "ef02da69-5ed6-4f41-94ab-d6b6da275b51"
  ],
  "etag": "hLb+xmvnlDygXcb9Sj7sncI3ZL0",
  "customMetadata": {},
  "timeCreated": "2023-08-01T10:17:36.984Z",
  "updated": "2023-08-01T10:17:36.984Z",
  "size": 58147,
  "md5Hash": "LuJ5hge4f5waCWdkcQd2sw==",
  "crc32c": "4276793452"
}